<?xml version="1.0" standalone="no" ?>
<!DOCTYPE pov SYSTEM "/usr/share/cgc-docs/replay.dtd">
<pov>
<cbid>service</cbid>
<replay>
<read>
<length>29</length>
</read>
<write>
<data>\xbf\x04\x04\x04\x04\x04\x04\x04\x67\x67\x23\x71\x63\x7a\xe6\xde\x2d\xec\xf5\x40\x3e\x28\xc8\x33\xbc\xe4\x02\x59\xca\x17\xbd\x1f\x78\x1c\x32\x85\xcd\x0c\x66\x07\x5e\xec\xd0\x68\xcf\x38\x0b\xc8\xc8\x7f\x10\x58\x53\xcb\x16\x94\x1c\xa5\x7e\x2f\x13\x10\x86\x38\x32\x9e\xb8\xde\xf3\x72\xd9\x51\x41\xd8\xad\x95\x70\x64\x15\x42\x18\x34\xcd\x20\x24\x37\x9f\x2d\xa5\xc0\x03\x38\x72\xae\x50\xbc\x6e\x19\x4a\xe5\x69\xa1\x56\x5b\x8c\x41\x11\xc7\x4a\x46\xa9\x98\x5d\x3e\x90\x7b\x3a\x07\xe4\x0e\xe2\x56\xae\xa6\xd1\x41\x37\x1f\x6a\x5b\x6d\xf7\x68\x82\x96\x4a\xe0\x4c\xc0\xb7\x29\xe1\x96\x76\x80\x0a\xdd\x9d\x4f\xe6\x2d\xdc\x2f\x80\xba\xb4\xfb\x94\x80\x19\x1f\xe2\x55\x16\xce\x35\x54\x8c\xaa\x09\xbc\x3b\xe9\xfd\x07\x1a\x9f\xbd\x92\x7e\xff\x8e\xf9\xc4\xf0\x33\x39\xeb\xaa\xe9\xf4\xa6\x6d\x14\xf7\xa3\x56\x05\x10\xbf\xa5\x60\x18\x54\x3f\x4a\x17\x52\xe3\x22\xa2\x91\xeb\x51\x44\x9c\x50\xc7\xab\x11\x47\x96\x79\x15\xf1\x89\x80\x30\x34\x87\x3b\x51\x61\x9c\x2b\x49\x69\x89\xa7\x32\x97\x87\xf4\xfa\xf1\x00\xc6\x57\xd9\x22\x76\xd4\xdd\xb6\x7c\x66\xdf\xe5\x53\x10\x38\x74\x5b\x6e\x9a\x98\x15\x33\x5a\xe5\x50\x2b\xb3\x38\x13\x1c\xd0\x85\x0f\xb0\x05\x0d\xd3\x3b\x20\xc3\x0d\xc4\x01\xdd\x83\xba\xbf\x70\xa9\xd2\x2e\xb5\xb1\xba\x36\x13\xde\x53\x84\x12\x87\xd2\x6c\x8e\x94\x7f\xfb\x94\x46\x2a\xce\xef\x23\xd0\x28\x53\xed\xd4\xae\x57\xc5\x54\x5f\x72\xb1\x87\x1c\xfd\xbd\x01\x19\x77\x16\xae\x98\x39\x2f\x9a\x66\x02\x23\xb0\x6f\x57\xff\x94\xeb\x10\xb2\x57\x1d\xa7\xab\x11\x70\x32\xb5\x1b\x9b\x84\x73\x65\xeb\xef\x93\x97\x8d\xfb\xc1\x26\xae\xda\x90\x9e\x1b\x09\x88\x5c\x06\x82\xa2\xe1\xb8\xc7\x62\x5a\x40\xb1\x66\x68\xf8\x91\x51\x0d\x9a\x2c\x7e\x00\x14\x78\xde\x7b\xe9\xad\xc5\xcb\x7e\xe1\x1f\xe9\x5b\x56\x08\x02\x87\x89\xfd\xe2\x49\x0c\x6d\xbc\xd0\x20\x0a\x76\xf6\x23\x69\xca\x7d\x57\x99\x7f\x43\x8a\x5a\x0d\xb8\xce\x4f\xe9\x3c\x6b\x72\xb7\x91\x64\xf5\xb9\x83\x86\x90\x57\xb2\x4c\xf2\x74\xe2\x3e\x87\xb5\x84\x2b\x39\xa3\x35\x6d\x40\xfe\xe1\x43\x5e\x18\x4b\xc6\x3a\x1c\xde\xcb\xd0\x70\x42\xcd\xf4\xae\xfc\xa1\x5c\xc7\x27\x4a\x0d\x1e\x52\x49\xf1\xd9\x0d\x9d\x24\x06\x06\x90\xf6\xf6\xa0\x5d\x83\xc1\xc6\x05\x13\x9c\xeb\x04\x5f\x9b\xb3\x0a\x93\x40\xfe\xc1\x4d\xe3\xed\xb4\x2d\x8f\xc8\xd5\x13\xbf\x6c\xc4\x2b\x55\xa6\x53\x1a\x66\x25\x6f\x1a\xaf\x27\x47\x5a\xae\x07\x9d\x2b\xdf\xa0\xc4\x21\x8f\x43\x2a\xa2\x53\xf5\x80\x02\x40\xc6\xe5\xdf\xbb\x68\xbf\x9f\xca\x87\xd9\x73\x3f\xa2\x56\x98\x84\x43\x3f\xea\x27\x89\xd1\x5d\xd6\xf2\xb7\x1a\x11\xbd\x60\x4e\xf3\x87\x48\x72\xea\x35\x76\xb5\x28\x7a\x1a\x31\xba\x29\x76\xb8\x12\xaf\xff\x5d\xf5\x2b\x0e\xe1\x2b\x27\xdd\x50\xab\xa2\x65\xaa\x15\x12\x46\xbc\xfb\x3d\x26\x78\x73\x1a\xa5\x78\xe2\xeb\x8f\xf8\xde\x9c\xb3\x94\x00\x63\xe0\x28\x43\xae\xc9\xcc\x62\x59\x2e\xfc\xcb\x57\x5d\x24\x23\xbd\x1b\xd9\x75\xe1\xe1\xcb\x00\xe8\x1c\xdc\xa1\x55\x11\x09\x3c\x32\x16\x68\xca\xc2\x35\xdc\xda\x5f\x0b\x20\x16\x6b\x2e\xcc\x99\xe2\x08\x89\x64\x7c\x83\xa4\xdb\x96\x13\x26\xc1\x1a\x58\x61\x08\x3e\x4d\xba\xea\xee\x44\x2f\x1e\x7e\x26\xfe\x9d\x99\x0b\x87\x18\x17\xbb\x81\x9c\x78\x7d\x07\x00\x11\x48\xe9\x65\x64\xd6\x3e\x96\x64\xd3\xcc\x00\xf6\xf0\xdb\xc9\x86\xb8\xb7\x8e\x80\xb3\xaa\xd9\x2a\x9e\xbd\x16\xdc\x35\x0c\x58\x62\x21\x38\xa0\x1c\xa2\x74\x5c\x80\xf6\x35\xef\x74\x40\x1e\xca\xa3\xde\x58\x70\xf1\x6d\x4a\x9d\x6e\xd1\x86\x42\x62\x5b\x4a\xc2\x7b\xe0\x93\x92\x2d\xa7\xd1\x0e\xcb\x6f\x07\x7f\x26\x20\xde\xc4\x15\x97\x61\xa6\x5a\x38\x30\x90\xd4\x74\x4e\x27\x71\x0c\x38\xeb\x59\xd2\x78\x39\x74\x30\x69\x15\x52\xd4\x96\x17\xe9\xf2\x76\xb2\xc7\xe5\x11\x76\xa1\x58\xd4\xb7\xd9\x2d\x36\xb6\x26\xd9\x81\x81\xba\x2d\x02\x4d\x2e\xbc\x9b\x2d\xc9\xf8\xf4\x50\x7b\x71\x56\x5d\x90\x3e\x89\xc7\xc9\xfa\xa7\x07\x72\x82\x25\xaf\x4d\xc4\x42\x4c\x52\x42\xfb\xc9\xf9\x39\x60\x84\x1e\x0b\x50\xa7\xca\xb4\x56\x6c\x18\x06\x5e\xa0\xc7\x12\x15\x23\x68\x71\x1f\x21\xe2\x7e\xc1\x40\x26\xcd\x5c\xa3\xc4\x8c\x90\x05\xe6\x54\xe3\x7c\x3d\xbc\x00\xbb\xd5\x20\x0b\x21\x71\xd0\xe3\xf8\x91\x40\xd2\x11\x2a\x1b\x62\xc8\x65\xb7\x4b\x22\xdf\xa5\xbd\x97\x6b\xb3\x57\x6c\xe5\x2f\xd3\x38\xd5\xfd\xec\x1e\x5f\x79\xff\xad\x65\xd4\xc7\x52\x97\xdb\xde\x7b\x07\x36\x07\x1d\x39\x85\x08\xcf\xf0\xe0\x65\x95\xc6\xa8\x77\x03\x72\xb0\xad\x5f\xf7\xb1\x62\xb0\xd1\x67\x74\xbb\xfa\x9d\x06\x5f\x75\x4d\x5e\x02\x03\xd8\x74\xb7\x6f\x6d\x5d\x07\x9a\xfc\xda\x5d\x6e\x08\xeb\xbb\xe0\x78\xce\x50\x59\xdd\xd7\xfc\x67\x88\xe7\xc1\xbd\x8a\x13\x0b\xb8\x8a\x91\x4f\x7b\x70\x43\xdd\xe8\xe5\x7e\x9c\x67\x0a\x98\xe8\x9d\x36\xfb\x0e\x81\x12\x82\xec\x6d\x1e\xfc\x99\x2f\x9e\x07\x21\xfa\xc1\x92\x62\x9f\x59\x2e\x98\xf4\xa8\x64\x9b\x80\xbc\x0e\x01\x30\x4a\xe0\x0f\xfc\xdf\xde\x97\x84\x7e\x27\x48\x1f\xb3\xeb\xe7\x23\x89\x86\x98\x66\xae\x2f\x3c\x98\xb2\xa7\xac\xbe\x05\xc2\xa8\x7a\xab\x0c\xfa\x10\xad\xcf\x32\x26\x22\x0f\x7e\xb8\x8d\x08\x56\x53\x7b\x7f\xa3\xa6\xc0\x6e\x41\x28\x0e\xe7\xb0\xf3\xf4\xcf\x50\xaa\xae\xc7\x2d\x8d\x89\x4e\x4b\xa8\xcd\xb1\x91\x02\x31\x08\x21\xec\xb6\x5f\xaf\x5c\x57\x07\xfa\x9e\x3b\xd0\xab\x64\x77\x3f\x49\xd3\x4a\xc7\xbc\x7b</data>
</write>
<read>
<length>99</length>
</read>
</replay>
</pov>
